{
    "logo": {
        "url": "/images/logo-white.svg",
        "altText": "Best Las Palmas",
        "type": "ImageBlock"
    },
    "text": "La asociación estudiantil más vibrante de Las Palmas. Conectamos estudiantes, creamos oportunidades y construimos el futuro juntos. 🌟",
    "primaryLinks": {
        "title": "Participa",
        "links": [
            {
                "label": "Eventos",
                "altText": "Próximos eventos",
                "url": "/eventos",
                "icon": "arrowRight",
                "iconPosition": "right",
                "style": "secondary",
                "type": "Link"
            },
            {
                "label": "Únete",
                "url": "/unete",
                "icon": "arrowRight",
                "iconPosition": "right",
                "style": "secondary",
                "type": "Link"
            },
            {
                "label": "Voluntariado",
                "url": "/voluntariado",
                "icon": "arrowRight",
                "iconPosition": "right",
                "style": "secondary",
                "type": "Link"
            }
        ],
        "type": "FooterLinksGroup"
    },
    "secondaryLinks": {
        "title": "Conoce más",
        "links": [
            {
                "label": "Sobre nosotros",
                "altText": "Quiénes somos",
                "url": "/sobre-nosotros",
                "icon": "arrowRight",
                "iconPosition": "right",
                "style": "secondary",
                "type": "Link"
            },
            {
                "label": "Blog",
                "url": "/blog",
                "icon": "arrowRight",
                "iconPosition": "right",
                "style": "secondary",
                "type": "Link"
            },
            {
                "label": "Contacto",
                "url": "/contacto",
                "icon": "arrowRight",
                "iconPosition": "right",
                "style": "secondary",
                "type": "Link"
            }
        ],
        "type": "FooterLinksGroup"
    },
    "socialLinks": [
        {
            "altText": "Instagram de Best Las Palmas",
            "url": "https://instagram.com/bestlaspalmas",
            "icon": "instagram",
            "type": "Social"
        },
        {
            "altText": "Twitter de Best Las Palmas",
            "url": "https://twitter.com/bestlaspalmas",
            "icon": "twitter",
            "type": "Social"
        },
        {
            "altText": "LinkedIn de Best Las Palmas",
            "url": "https://www.linkedin.com/company/bestlaspalmas",
            "icon": "linkedin",
            "type": "Social"
        },
        {
            "altText": "Email de contacto",
            "url": "mailto:hola@bestlaspalmas.com",
            "icon": "mail",
            "type": "Social"
        }
    ],
    "legalLinks": [
        {
            "label": "Términos",
            "url": "/terminos",
            "icon": "arrowRight",
            "iconPosition": "right",
            "style": "secondary",
            "type": "Link"
        },
        {
            "label": "Privacidad",
            "url": "/privacidad",
            "icon": "arrowRight",
            "iconPosition": "right",
            "style": "secondary",
            "type": "Link"
        }
    ],
    "copyrightText": "© 2025 Best Las Palmas. Hecho con ❤️ por estudiantes para estudiantes.\n",
    "colors": "bg-dark-fg-light",
    "type": "Footer"
}